pytearcat/__init__.py
pytearcat/gr/__init__.py
pytearcat/gr/christoffel.py
pytearcat/gr/einstein.py
pytearcat/gr/geodesic.py
pytearcat/gr/metric.py
pytearcat/gr/ricci.py
pytearcat/gr/riemann.py
pytearcat/tensor/__init__.py
pytearcat/tensor/kdelta.py
pytearcat/tensor/lcivita.py
pytearcat/tensor/misc.py
pytearcat/tensor/tensor.py
pytearcat/tensor/core/__init__.py
pytearcat/tensor/core/config.py
pytearcat/tensor/core/core.py
pytearcat/tensor/core/display.py
pytearcat/tensor/core/distribute.py
pytearcat/tensor/core/error.py
pytearcat/tensor/core/fun.py
pytearcat/tensor/core/gpwrap.py
pytearcat/tensor/core/greek.py
pytearcat/tensor/core/interp.py
pytearcat/tensor/core/ptseries.py
pytearcat/tensor/core/tdata.py
tests/__init__.py
tests/test_notebooks.py
pytearcat-0.0.8.dist-info/LICENSE
pytearcat-0.0.8.dist-info/METADATA
pytearcat-0.0.8.dist-info/WHEEL
pytearcat-0.0.8.dist-info/top_level.txt
pytearcat-0.0.8.dist-info/RECORD
